MANIFEST.in
setup.py
Cuckoo_common.egg-info/PKG-INFO
Cuckoo_common.egg-info/SOURCES.txt
Cuckoo_common.egg-info/dependency_links.txt
Cuckoo_common.egg-info/not-zip-safe
Cuckoo_common.egg-info/requires.txt
Cuckoo_common.egg-info/top_level.txt
cuckoo/common/__init__.py